mlxpose/__init__.py
mlxpose/_nbdev.py
xpose/__init__.py
xpose/_nbdev.py
mlxpose-0.0.0.dist-info/LICENSE
mlxpose-0.0.0.dist-info/METADATA
mlxpose-0.0.0.dist-info/WHEEL
mlxpose-0.0.0.dist-info/entry_points.txt
mlxpose-0.0.0.dist-info/top_level.txt
mlxpose-0.0.0.dist-info/RECORD
