Metadata-Version: 2.1
Name: mlxpose
Version: 0.0.0
Summary: Expose ML black boxes
Home-page: https://github.com/So-Cool/mlxpose/tree/master/
Author: Kacper Sokol
Author-email: ks1591@my.bristol.ac.uk
License: BSD License
Keywords: xai,iml
Platform: UNKNOWN
Classifier: Development Status :: 1 - Planning
Classifier: Intended Audience :: Developers
Classifier: Natural Language :: English
Classifier: Programming Language :: Python :: 3.6
Classifier: Programming Language :: Python :: 3.7
Classifier: Programming Language :: Python :: 3.8
Classifier: License :: OSI Approved :: BSD License
Requires-Python: >=3.6
